ShittyPackage/__init__.py
ShittyPackage/src.py
shittypackage-0.0.1.dist-info/METADATA
shittypackage-0.0.1.dist-info/WHEEL
shittypackage-0.0.1.dist-info/top_level.txt
shittypackage-0.0.1.dist-info/RECORD
